KeePassDiff/__init__.py
KeePassDiff/__main__.py
KeePassDiff/app.py
KeePassDiff/components/entry_modal.py
KeePassDiff/launch.py
KeePassDiff/utils/comparison.py
KeePassDiff/utils/database.py
keepassdiff-0.1.12.dist-info/entry_points.txt
keepassdiff-0.1.12.dist-info/LICENSE
keepassdiff-0.1.12.dist-info/METADATA
keepassdiff-0.1.12.dist-info/WHEEL
keepassdiff-0.1.12.dist-info/RECORD
