Metadata-Version: 2.1
Name: keepassdiff
Version: 0.1.12
Summary: A diff/merge tool for KeePassXC databases
License: MIT
Author: Billy
Author-email: billydevbusiness@gmail.com
Requires-Python: >=3.12,<4.0
Classifier: License :: OSI Approved :: MIT License
Classifier: Programming Language :: Python :: 3
Classifier: Programming Language :: Python :: 3.12
Requires-Dist: pykeepass (>=4.1.0.post1,<5.0.0)
Requires-Dist: streamlit (>=1.40.2,<2.0.0)
